{
    "meta": {
        "trc": 74930,
        "division": "Open Mint League Division B",
        "racingSeason": "2025/26",
        "team": {
            "tttid": 18013,
            "teamid": 18013,
            "name": "Team INOX Trinacria",
            "jerseyname": "Team INOX",
            "jerseyimage": "INOX2025_thumb",
            "recruiting": false,
            "isdev": false
        },
        "nextRace": {
            "teamstart": null,
            "raceFormat": ""
        },
        "competition": {
            "wtrlid": "ZRL",
            "season": 18,
            "sportsYear": 2025,
            "roundnumber": 1,
            "division": "B",
            "class": "2360B0",
            "status": "REGISTERED",
            "registered": [
                "1",
                "2",
                "3",
                "4"
            ]
        },
        "memberCount": 4,
        "membersRemaining": 8,
        "administrators": {
            "registerer": {
                "firstName": "Miky",
                "lastName": "Tedesco",
                "profileId": 1152951,
                "userId": "8991fae8-ec2f-48bb-ba75-1f09d130ad63"
            },
            "captain": {
                "firstName": "Miky",
                "lastName": "Tedesco",
                "profileId": 1152951,
                "userId": "8991fae8-ec2f-48bb-ba75-1f09d130ad63"
            },
            "managers": [
                {
                    "firstName": "Street",
                    "lastName": "Hawk",
                    "profileId": 7072727,
                    "userId": "6075bb3f-add5-45c5-a355-096458c4917a"
                }
            ]
        }
    },
    "permissions": {
        "id": 7072727,
        "isAdmin": true
    },
    "riders": [
        {
            "tmuid": 418033,
            "name": "Andrea Falchetti",
            "avatar": "/uploads/profile_picture/1730758950_Screenshot_20241104_211553_Gallery.jpg",
            "memberStatus": "MEMBER",
            "signedup": false,
            "category": "B",
            "zftp": 3.41,
            "zftpw": 260,
            "zmapw": 343,
            "zmap": 4.5,
            "riderpoints": 0,
            "teams": 0,
            "appearancesRound": 0,
            "appearancesSeason": 6,
            "profileId": 3432509,
            "userId": "d393f485-51f2-435e-9801-da4ec71a35eb"
        },
        {
            "tmuid": 418027,
            "name": "Ricardo Santos",
            "avatar": "/uploads/profile_picture/1727457203_20240730_080848.jpg",
            "memberStatus": "MEMBER",
            "signedup": false,
            "category": "B",
            "zftp": 4.15,
            "zftpw": 365,
            "zmapw": 419,
            "zmap": 4.76,
            "riderpoints": 0,
            "teams": 0,
            "appearancesRound": 0,
            "appearancesSeason": 3,
            "profileId": 164627,
            "userId": "b777c4ab-2990-46ba-910a-ae6aaecb21f9"
        },
        {
            "tmuid": 418036,
            "name": "Simone Oppezzo",
            "avatar": "https://static-cdn.zwift.com/prod/profile/3d5b66e3-263432",
            "memberStatus": "MEMBER",
            "signedup": false,
            "category": "B",
            "zftp": 3.34,
            "zftpw": 228,
            "zmapw": 283,
            "zmap": 4.15,
            "riderpoints": 0,
            "teams": 0,
            "appearancesRound": 0,
            "appearancesSeason": 2,
            "profileId": 475715,
            "userId": "0af9f313-aebc-443a-a7e8-a1c41d1e36d0"
        },
        {
            "tmuid": 421723,
            "name": "Mario Cavallaro",
            "avatar": "https://static-cdn.zwift.com/prod/profile/93b07a23-1459691",
            "memberStatus": "INVITED",
            "signedup": false,
            "category": "B",
            "zftp": 3.55,
            "zftpw": 286,
            "zmapw": 330,
            "zmap": 4.1,
            "riderpoints": 0,
            "teams": 0,
            "appearancesRound": 0,
            "appearancesSeason": 0,
            "profileId": 2690375,
            "userId": "b5ce339e-e11b-4e9f-939a-76d7d5d8ec81"
        }
    ]
}